<?xml version="1.0" encoding="utf-8" ?>
<c2layout>
    <name>Main</name>
    <sid>1014813501000418</sid>
    <event-sheet>Events - Main</event-sheet>
    <size>
        <width>1280</width>
        <height>800</height>
    </size>
    <margins>
        <horizontal>0</horizontal>
        <vertical>0</vertical>
    </margins>
    <unbounded-scrolling>1</unbounded-scrolling>
    <layers>
        <layer name="background" sid="2774119635813765">
            <initially-visible>1</initially-visible>
            <background-color>255,255,255</background-color>
            <transparent>0</transparent>
            <parallax>
                <x>1</x>
                <y>1</y>
            </parallax>
            <zoom-rate>1</zoom-rate>
            <opacity>1</opacity>
            <force-own-texture>0</force-own-texture>
            <blend-mode>0</blend-mode>
            <effect-fallback>0</effect-fallback>
            <instances>
                <instance type="TiledBackground02" uid="22">
                    <properties>
                        <initial-visibility>Visible</initial-visibility>
                        <hotspot>Top-left</hotspot>
                    </properties>
                    <blend-mode>0</blend-mode>
                    <effect-fallback>0</effect-fallback>
                    <world>
                        <x>0</x>
                        <y>0</y>
                        <z>0</z>
                        <width>1280</width>
                        <height>800</height>
                        <depth>0</depth>
                        <hotspotX>0</hotspotX>
                        <hotspotY>0</hotspotY>
                        <angle>0</angle>
                        <opacity>1</opacity>
                    </world>
                </instance>
            </instances>
            <effects />
        </layer>
        <layer name="foreground" sid="8255440789017194">
            <initially-visible>1</initially-visible>
            <background-color>255,255,255</background-color>
            <transparent>1</transparent>
            <parallax>
                <x>0</x>
                <y>0</y>
            </parallax>
            <zoom-rate>0</zoom-rate>
            <opacity>1</opacity>
            <force-own-texture>0</force-own-texture>
            <blend-mode>0</blend-mode>
            <effect-fallback>0</effect-fallback>
            <instances>
                <instance type="TextDebug" uid="24">
                    <properties>
                        <text>Text</text>
                        <initial-visibility>Visible</initial-visibility>
                        <font>Arial,-19,400,0</font>
                        <color>255,255,255</color>
                        <horizontal-alignment>Left</horizontal-alignment>
                        <vertical-alignment>Top</vertical-alignment>
                        <hotspot>Top-left</hotspot>
                        <wrapping>Word</wrapping>
                        <line-height>0</line-height>
                    </properties>
                    <behavior-instances>
                        <behavior-instance type="Anchor">
                            <properties>
                                <left-edge>Window left</left-edge>
                                <top-edge>Window top</top-edge>
                                <right-edge>None</right-edge>
                                <bottom-edge>None</bottom-edge>
                                <initial-state>Enabled</initial-state>
                            </properties>
                        </behavior-instance>
                    </behavior-instances>
                    <blend-mode>0</blend-mode>
                    <effect-fallback>0</effect-fallback>
                    <world>
                        <x>10</x>
                        <y>10</y>
                        <z>0</z>
                        <width>672</width>
                        <height>119</height>
                        <depth>0</depth>
                        <hotspotX>0</hotspotX>
                        <hotspotY>0</hotspotY>
                        <angle>0</angle>
                        <opacity>1</opacity>
                    </world>
                </instance>
                <instance type="Handle" uid="10">
                    <properties>
                        <initial-visibility>Visible</initial-visibility>
                        <initial-animation>Default</initial-animation>
                        <initial-frame>0</initial-frame>
                        <collisions>Enabled</collisions>
                    </properties>
                    <behavior-instances>
                        <behavior-instance type="Physics">
                            <properties>
                                <immovable>Yes</immovable>
                                <collision-mask>Use collision polygon</collision-mask>
                                <prevent-rotation>No</prevent-rotation>
                                <density>1</density>
                                <friction>0.5</friction>
                                <elasticity>0.2</elasticity>
                                <linear-damping>0</linear-damping>
                                <angular-damping>0.01</angular-damping>
                                <bullet>No</bullet>
                                <initial-state>Enabled</initial-state>
                            </properties>
                        </behavior-instance>
                        <behavior-instance type="DragDrop">
                            <properties>
                                <axes>Both</axes>
                                <initial-state>Enabled</initial-state>
                            </properties>
                        </behavior-instance>
                    </behavior-instances>
                    <blend-mode>0</blend-mode>
                    <effect-fallback>0</effect-fallback>
                    <world>
                        <x>168</x>
                        <y>-116</y>
                        <z>0</z>
                        <width>100</width>
                        <height>100</height>
                        <depth>0</depth>
                        <hotspotX>0.5</hotspotX>
                        <hotspotY>0.5</hotspotY>
                        <angle>0</angle>
                        <opacity>1</opacity>
                    </world>
                </instance>
                <instance type="UIButton" uid="20">
                    <properties>
                        <initial-visibility>Visible</initial-visibility>
                        <initial-animation>Default</initial-animation>
                        <initial-frame>0</initial-frame>
                        <collisions>Enabled</collisions>
                    </properties>
                    <instance-variables>
                        <title>collect</title>
                    </instance-variables>
                    <behavior-instances>
                        <behavior-instance type="Anchor">
                            <properties>
                                <left-edge>Window left</left-edge>
                                <top-edge>Window top</top-edge>
                                <right-edge>None</right-edge>
                                <bottom-edge>None</bottom-edge>
                                <initial-state>Enabled</initial-state>
                            </properties>
                        </behavior-instance>
                    </behavior-instances>
                    <blend-mode>0</blend-mode>
                    <effect-fallback>0</effect-fallback>
                    <world>
                        <x>620</x>
                        <y>260</y>
                        <z>0</z>
                        <width>436</width>
                        <height>118</height>
                        <depth>0</depth>
                        <hotspotX>0.467741936</hotspotX>
                        <hotspotY>0.447761208</hotspotY>
                        <angle>0</angle>
                        <opacity>1</opacity>
                    </world>
                </instance>
                <instance type="UIButton" uid="23">
                    <properties>
                        <initial-visibility>Visible</initial-visibility>
                        <initial-animation>Default</initial-animation>
                        <initial-frame>0</initial-frame>
                        <collisions>Enabled</collisions>
                    </properties>
                    <instance-variables>
                        <title>create</title>
                    </instance-variables>
                    <behavior-instances>
                        <behavior-instance type="Anchor">
                            <properties>
                                <left-edge>Window left</left-edge>
                                <top-edge>Window top</top-edge>
                                <right-edge>None</right-edge>
                                <bottom-edge>None</bottom-edge>
                                <initial-state>Enabled</initial-state>
                            </properties>
                        </behavior-instance>
                    </behavior-instances>
                    <blend-mode>0</blend-mode>
                    <effect-fallback>0</effect-fallback>
                    <world>
                        <x>620</x>
                        <y>400</y>
                        <z>0</z>
                        <width>436</width>
                        <height>118</height>
                        <depth>0</depth>
                        <hotspotX>0.467741936</hotspotX>
                        <hotspotY>0.447761208</hotspotY>
                        <angle>0</angle>
                        <opacity>1</opacity>
                    </world>
                </instance>
                <instance type="UIButton" uid="25">
                    <properties>
                        <initial-visibility>Visible</initial-visibility>
                        <initial-animation>Default</initial-animation>
                        <initial-frame>0</initial-frame>
                        <collisions>Enabled</collisions>
                    </properties>
                    <instance-variables>
                        <title>decorate</title>
                    </instance-variables>
                    <behavior-instances>
                        <behavior-instance type="Anchor">
                            <properties>
                                <left-edge>Window left</left-edge>
                                <top-edge>Window top</top-edge>
                                <right-edge>None</right-edge>
                                <bottom-edge>None</bottom-edge>
                                <initial-state>Enabled</initial-state>
                            </properties>
                        </behavior-instance>
                    </behavior-instances>
                    <blend-mode>0</blend-mode>
                    <effect-fallback>0</effect-fallback>
                    <world>
                        <x>620</x>
                        <y>540</y>
                        <z>0</z>
                        <width>436</width>
                        <height>118</height>
                        <depth>0</depth>
                        <hotspotX>0.467741936</hotspotX>
                        <hotspotY>0.447761208</hotspotY>
                        <angle>0</angle>
                        <opacity>1</opacity>
                    </world>
                </instance>
            </instances>
            <effects />
        </layer>
    </layers>
    <nonworld-instances />
    <effects />
</c2layout>
